LICENSE.txt
flask_sqlalchemy_pgevents.py
flask_sqlalchemy_pgevents-0.3.0.dist-info/LICENSE.txt
flask_sqlalchemy_pgevents-0.3.0.dist-info/WHEEL
flask_sqlalchemy_pgevents-0.3.0.dist-info/METADATA
flask_sqlalchemy_pgevents-0.3.0.dist-info/RECORD
