Metadata-Version: 2.1
Name: flask-sqlalchemy-pgevents
Version: 0.3.0
Summary: Flask extension for psycopg2-pgevents, using SQLAlchemy.
Home-page: https://github.com/shawalli/flask-sqlalchemy-pgevents
License: MIT
Author: Shawn Wallis
Author-email: shawn.p.wallis@gmail.com
Requires-Python: >=3.7,<4.0
Classifier: Development Status :: 3 - Alpha
Classifier: Environment :: Web Environment
Classifier: Intended Audience :: Developers
Classifier: License :: OSI Approved :: MIT License
Classifier: Operating System :: OS Independent
Classifier: Programming Language :: Python :: 3
Classifier: Programming Language :: Python :: 3.7
Classifier: Programming Language :: Python :: 3.8
Classifier: Topic :: Database
Classifier: Topic :: Software Development :: Libraries :: Python Modules
Classifier: Topic :: Utilities
Requires-Dist: attr (>=0.3.1,<0.4.0)
Requires-Dist: flask (>=1.1.2,<2.0.0)
Requires-Dist: flask-sqlalchemy (>=2.4.4,<3.0.0)
Requires-Dist: github-webhook (>=1.0.2,<2.0.0)
Requires-Dist: psycopg2-binary (>=2.8.5,<3.0.0)
Requires-Dist: psycopg2-pgevents (>=0.2.1,<0.3.0)
Project-URL: Repository, https://github.com/shawalli/flask-sqlalchemy-pgevents
